ultradl_pro/__init__.py
ultradl_pro/__main__.py
ultradl_pro/cli.py
ultradl_pro/py.typed
ultradl_pro-0.1.1.dist-info/licenses/LICENSE
ultradl_pro-0.1.1.dist-info/METADATA
ultradl_pro-0.1.1.dist-info/WHEEL
ultradl_pro-0.1.1.dist-info/entry_points.txt
ultradl_pro-0.1.1.dist-info/top_level.txt
ultradl_pro-0.1.1.dist-info/RECORD
