Metadata-Version: 2.4
Name: ultradl-pro
Version: 0.1.1
Summary: UltraDL Pro - cross-platform CLI downloader powered by yt-dlp
Author: UltraDL Pro
License-Expression: MIT
Keywords: download,downloader,yt-dlp,youtube,cli
Classifier: Environment :: Console
Classifier: Intended Audience :: End Users/Desktop
Classifier: Programming Language :: Python :: 3
Classifier: Programming Language :: Python :: 3 :: Only
Classifier: Programming Language :: Python :: 3.9
Classifier: Programming Language :: Python :: 3.10
Classifier: Programming Language :: Python :: 3.11
Classifier: Programming Language :: Python :: 3.12
Classifier: Programming Language :: Python :: 3.13
Classifier: Operating System :: OS Independent
Requires-Python: >=3.9
License-File: LICENSE
Requires-Dist: yt-dlp>=2025.11.12
Requires-Dist: rich>=13.7.0
Requires-Dist: platformdirs>=4.0.0
Provides-Extra: spotify
Requires-Dist: spotdl>=4.2.0; extra == "spotify"
Dynamic: license-file
